kudubot/Bot.py
kudubot/__init__.py
kudubot/exceptions.py
kudubot/helper.py
kudubot/db/Address.py
kudubot/db/__init__.py
kudubot/db/config/DbConfig.py
kudubot/db/config/__init__.py
kudubot/db/config/impl/MySqlConfig.py
kudubot/db/config/impl/SqlteConfig.py
kudubot/db/config/impl/__init__.py
kudubot/parsing/Command.py
kudubot/parsing/CommandParser.py
kudubot/parsing/__init__.py
kudubot/test/__init__.py
kudubot-0.33.0.dist-info/LICENSE
kudubot-0.33.0.dist-info/METADATA
kudubot-0.33.0.dist-info/WHEEL
kudubot-0.33.0.dist-info/top_level.txt
kudubot-0.33.0.dist-info/RECORD
