Metadata-Version: 2.1
Name: kudubot
Version: 0.33.0
Summary: An chat bot framework
Home-page: https://gitlab.namibsun.net/namibsun/python/kudubot
Author: Hermann Krumrey
Author-email: hermann@krumreyh.com
License: GNU GPL3
Platform: UNKNOWN
Classifier: License :: OSI Approved :: GNU General Public License v3 (GPLv3)
Requires-Dist: typing
Requires-Dist: bokkichat
Requires-Dist: sqlalchemy
Requires-Dist: sentry-sdk
Requires-Dist: puffotter
